kielbasa/__init__.py
kielbasa-0.0.2.dist-info/METADATA
kielbasa-0.0.2.dist-info/WHEEL
kielbasa-0.0.2.dist-info/top_level.txt
kielbasa-0.0.2.dist-info/RECORD
