Metadata-Version: 2.1
Name: kielbasa
Version: 0.0.2
Summary: All-Natural Casing Utilities
Home-page: https://github.com/joshingmachine/kielbasa
Author: Josh Smith
Author-email: josh@joshingmachine.com
License: UNKNOWN
Platform: UNKNOWN
Classifier: Programming Language :: Python :: 3
Classifier: License :: OSI Approved :: MIT License
Classifier: Operating System :: OS Independent
Requires-Python: >=3.6
